Workbook
Name aporte: 'Ferramenta de Controle de Inves'!$D$17
Name patrimonio: 'Ferramenta de Controle de Inves'!$D$20
Name qtde_anos: 'Ferramenta de Controle de Inves'!$D$18
Name Rendimento_Carteira: 'Ferramenta de Controle de Inves'!$D$13
Name salario: 'Ferramenta de Controle de Inves'!$D$12
Name sugestao_investimento: 'Ferramenta de Controle de Inves'!$D$14
Name taxa_mensal: 'Ferramenta de Controle de Inves'!$D$19

Sheet Ferramenta de Controle de Inves
B12: Salário | D12: 2000
B13: Rendimento | D13: 0.006
B14: Sugestão Investimento (30%) | D14: =D12*30% -> 600
A17: 2 | B17: Quanto investir por mês? | D17: 495
A18: 5 | B18: Por quantos anos? | D18: 2
A19: 10 | B19: Taxa de Rendimento mensal? | D19: 0.006
A20: 20 | B20: Quanto de Patrimônio acumulado? | D20: =FV(taxa_mensal,qtde_anos*12,aporte*-1) -> 12736.952
A21: 30 | B21: Dividendos mensais? | D21: =patrimonio*Rendimento_Carteira -> 76.42171
B24: Em 2 anos | C24: =FV(taxa_mensal,$A17*12,aporte*-1) -> 12736.952 | D24: =C24*Rendimento_Carteira -> 76.42171
B25: Em 5 anos | C25: =FV(taxa_mensal,$A18*12,aporte*-1) -> 35622.544 | D25: =C25*Rendimento_Carteira -> 213.73526
B26: Em 10 anos | C26: =FV(taxa_mensal,$A19*12,aporte*-1) -> 86626.49 | D26: =C26*Rendimento_Carteira -> 519.75894
B27: Em 20 anos | C27: =FV(taxa_mensal,$A20*12,aporte*-1) -> 264212.36 | D27: =C27*Rendimento_Carteira -> 1585.2741
B28: Em 30 anos | C28: =FV(taxa_mensal,$A21*12,aporte*-1) -> 628266.59 | D28: =C28*Rendimento_Carteira -> 3769.5996
C31: Moderado | D31: =aporte -> 495
B34: TIPO DE FII | C34: Percentual Sugerido | D34: Valores
B35: Papel | C35: =VLOOKUP($C$31&"-"&B35,Planilha2!A2:$D$20,4,FALSE) -> 0.32 | D35: =C35*$D$31 -> 158.4
B36: Tijolo | C36: =VLOOKUP($C$31&"-"&B36,Planilha2!A3:$D$20,4,FALSE) -> 0.35 | D36: =C36*$D$31 -> 173.25
B37: Desenvolvimento | C37: =VLOOKUP($C$31&"-"&B37,Planilha2!A4:$D$20,4,FALSE) -> 0.1 | D37: =C37*$D$31 -> 49.5
B38: Híbridos | C38: =VLOOKUP($C$31&"-"&B38,Planilha2!A5:$D$20,4,FALSE) -> 0.08 | D38: =C38*$D$31 -> 39.6
B39: FOFs | C39: =VLOOKUP($C$31&"-"&B39,Planilha2!A6:$D$20,4,FALSE) -> 0.05 | D39: =C39*$D$31 -> 24.75
B40: Hotelarias | C40: =VLOOKUP($C$31&"-"&B40,Planilha2!A7:$D$20,4,FALSE) -> 0.1 | D40: =C40*$D$31 -> 49.5
B41: TOTAL | D41: =SUM(D35:D40) -> 495

Sheet Planilha2
A2: Chave | B2: Perfil | C2: Tipo de FII | D2: %
A3: =B3&"-"&C3 -> Conservador-Papel | B3: Conservador | C3: Papel | D3: 0.3
A4: =B4&"-"&C4 -> Conservador-Tijolo | B4: Conservador | C4: Tijolo | D4: 0.4
A5: =B5&"-"&C5 -> Conservador-Desenvolvimento | B5: Conservador | C5: Desenvolvimento | D5: 0.05
A6: =B6&"-"&C6 -> Conservador-Híbridos | B6: Conservador | C6: Híbridos | D6: 0.1
A7: =B7&"-"&C7 -> Conservador-FOFs | B7: Conservador | C7: FOFs | D7: 0.1
A8: =B8&"-"&C8 -> Conservador-Hotelarias | B8: Conservador | C8: Hotelarias | D8: 0.05
A9: =B9&"-"&C9 -> Moderado-Papel | B9: Moderado | C9: Papel | D9: 0.32
A10: =B10&"-"&C10 -> Moderado-Tijolo | B10: Moderado | C10: Tijolo | D10: 0.35
A11: =B11&"-"&C11 -> Moderado-Desenvolvimento | B11: Moderado | C11: Desenvolvimento | D11: 0.1
A12: =B12&"-"&C12 -> Moderado-Híbridos | B12: Moderado | C12: Híbridos | D12: 0.08
A13: =B13&"-"&C13 -> Moderado-FOFs | B13: Moderado | C13: FOFs | D13: 0.05
A14: =B14&"-"&C14 -> Moderado-Hotelarias | B14: Moderado | C14: Hotelarias | D14: 0.1
... A20: =B20&"-"&C20 -> Agressivo-Hotelarias | B20: Agressivo | C20: Hotelarias | D20: 0.1
